.gitignore
.travis.yml
AUTHORS
LICENSE
MANIFEST.in
Makefile
README.md
make.bat
requirements.txt
setup.py
tox.ini
demo/game.hy
demo/game.py
demo/makengamesolver.hy
demo/makengamesolver.py
py2hyb/__init__.py
py2hyb/prettyprinter.hy
py2hyb/py2hy.hy
py2hyb/py2hy.py
py2hyb.egg-info/PKG-INFO
py2hyb.egg-info/SOURCES.txt
py2hyb.egg-info/dependency_links.txt
py2hyb.egg-info/entry_points.txt
py2hyb.egg-info/requires.txt
py2hyb.egg-info/top_level.txt
scripts/py2hy.sh
tests/__init__.py
tests/test_compiling.hy
tests/test_ops.hy
tools/parse_pygrammarspecs.py
tools/pygrammarspecs.txt
tools/template.hy